hypernn/__init__.py
hypernn/base.py
hypernn/jax/__init__.py
hypernn/jax/dynamic_hypernet.py
hypernn/jax/hypernet.py
hypernn/jax/linear_hypernet.py
hypernn/jax/utils.py
hypernn/torch/__init__.py
hypernn/torch/dynamic_hypernet.py
hypernn/torch/hypernet.py
hypernn/torch/linear_hypernet.py
hypernn/torch/utils.py
hyper_nn-0.2.2.dist-info/LICENSE
hyper_nn-0.2.2.dist-info/METADATA
hyper_nn-0.2.2.dist-info/WHEEL
hyper_nn-0.2.2.dist-info/top_level.txt
hyper_nn-0.2.2.dist-info/RECORD
