Metadata-Version: 2.1
Name: hyper-nn
Version: 0.2.2
Summary: Easy hypernetworks in Pytorch and Flax
Home-page: https://github.com/shyamsn97/hyper-nn
Author: Shyam Sudhakaran
Author-email: shyamsnair@protonmail.com
License: MIT
Platform: UNKNOWN
Classifier: Development Status :: 2 - Pre-Alpha
Classifier: License :: OSI Approved :: MIT License
Classifier: Programming Language :: Python :: 3.8
Classifier: Programming Language :: Python :: 3.9
License-File: LICENSE
Requires-Dist: numpy
Requires-Dist: torch
Requires-Dist: flax
Requires-Dist: jax
